osbot_gsuite/Deploy.py
osbot_gsuite/__init__.py
osbot_gsuite/analysis/Incident_Mass_Delete.py
osbot_gsuite/apis/GCalendar.py
osbot_gsuite/apis/GDrive_Activity.py
osbot_gsuite/apis/GPeople.py
osbot_gsuite/apis/GSheet.py
osbot_gsuite/apis/GSheets.py
osbot_gsuite/apis/GSuite_Admin.py
osbot_gsuite/apis/GSuite_Setup.py
osbot_gsuite/apis/GTypes.py
osbot_gsuite/apis/__init__.py
osbot_gsuite/apis/commands/Calendar_Commands.py
osbot_gsuite/apis/commands/GDocs_Commands.py
osbot_gsuite/apis/commands/Sheets_Commands.py
osbot_gsuite/apis/commands/Slides_Commands.py
osbot_gsuite/apis/commands/__init__.py
osbot_gsuite/apis/create_slides/GSBot_Helpers.py
osbot_gsuite/apis/create_slides/GSBot_to_GDrive.py
osbot_gsuite/apis/create_slides/Project_Slides.py
osbot_gsuite/apis/create_slides/Slides_for_Projects.py
osbot_gsuite/apis/create_slides/__init__.py
osbot_gsuite/apis/handlers/Lambda_Calendar.py
osbot_gsuite/apis/handlers/Lambda_GDocs.py
osbot_gsuite/apis/handlers/Lambda_Sheets.py
osbot_gsuite/apis/handlers/Lambda_Slides.py
osbot_gsuite/apis/handlers/__init__.py
osbot_gsuite/apis/sheets/API_Jira_Sheets_Create.py
osbot_gsuite/apis/sheets/API_Jira_Sheets_Sync.py
osbot_gsuite/apis/sheets/__init__.py
osbot_gsuite/apis/utils/GDoc_Named_Range.py
osbot_gsuite/apis/utils/GDrive_Folder.py
osbot_gsuite/gsuite/GSuite.py
osbot_gsuite/gsuite/__init__.py
osbot_gsuite/gsuite/docs/GDoc.py
osbot_gsuite/gsuite/docs/GDocs.py
osbot_gsuite/gsuite/docs/Temp__GDocs__File.py
osbot_gsuite/gsuite/docs/__init__.py
osbot_gsuite/gsuite/drive/GDrive.py
osbot_gsuite/gsuite/drive/Temp__GDrive__Folder.py
osbot_gsuite/gsuite/drive/__init__.py
osbot_gsuite/gsuite/slides/GSlides.py
osbot_gsuite/gsuite/slides/Temp__GSlides__Presentation.py
osbot_gsuite/gsuite/slides/__init__.py
osbot_gsuite/lambdas/__init__.py
osbot_gsuite/lambdas/calendar.py
osbot_gsuite/lambdas/gdocs.py
osbot_gsuite/lambdas/sheets.py
osbot_gsuite/lambdas/slides.py
osbot_gsuite/testing/OSBot__GSuite__Testing.py
osbot_gsuite/testing/__init__.py
osbot_gsuite-0.5.0.dist-info/LICENSE
osbot_gsuite-0.5.0.dist-info/METADATA
osbot_gsuite-0.5.0.dist-info/WHEEL
osbot_gsuite-0.5.0.dist-info/RECORD
