Metadata-Version: 2.1
Name: osbot_gsuite
Version: 0.5.0
Summary: OWASP GSuite
Home-page: https://github.com/owasp-sbot/OSBot-GSuite
License: MIT
Author: Dinis Cruz
Author-email: dinis.cruz@owasp.org
Requires-Python: >=3.11,<4.0
Classifier: License :: OSI Approved :: MIT License
Classifier: Programming Language :: Python :: 3
Classifier: Programming Language :: Python :: 3.11
Classifier: Programming Language :: Python :: 3.12
Requires-Dist: google-api-python-client
Requires-Dist: google-auth
Requires-Dist: google-auth-httplib2
Requires-Dist: google-auth-oauthlib
Requires-Dist: osbot-aws
Project-URL: Repository, https://github.com/owasp-sbot/OSBot-GSuite
